{
  "object_id": "roof_wind_gust_speed",
  "unique_id": "roof_wind_gust_speed",
  "name": "Roof Weather Station Roof Wind Gust Speed",
  "state_class": "measurement",
  "unit_of_measurement": "km/h",
  "icon": "mdi:weather-windy",
  "force_update": "false",
  "state_topic": "weewx/roof_wind_gust_speed",
  "value_template": "{{ value | float(None) }}",
  "qos": "1",
  "device": {
    "via_device": "WeeWX",
    "identifiers": "davis-roof-weather-station",
    "name": "Roof Weather Station",
    "model": "Vantage Pro2",
    "manufacturer": "Davis",
    "sw_version": "4.10.2",
    "suggested_area": "Roof"
  }
}
